pyrrr/__init__.py
pyrrr-0.1.0a0.dist-info/LICENSE
pyrrr-0.1.0a0.dist-info/WHEEL
pyrrr-0.1.0a0.dist-info/METADATA
pyrrr-0.1.0a0.dist-info/RECORD
